<?xml version="1.0" encoding="UTF-8"?>
<persistence xmlns="http://java.sun.com/xml/ns/persistence"
             xmlns:xsi="http://www.w3.org/2001/XMLSchema-instance"
             xsi:schemaLocation="http://java.sun.com/xml/ns/persistence http://java.sun.com/xml/ns/persistence/persistence_2_0.xsd"
             version="2.0">
    <persistence-unit name="search-share">
        <class>pt.maisis.search.entity.Report</class>
        <class>pt.maisis.search.entity.OrderParam</class>
        <class>pt.maisis.search.entity.SearchParam</class>
        <class>pt.maisis.search.entity.ResultParam</class>
        <class>pt.maisis.search.entity.ReportEntity</class>
    </persistence-unit>
</persistence>
